algo_beast/__init__.py
algo_beast/cmd/__init__.py
algo_beast/cmd/commands.py
algo_beast/cmd/initializer.py
algo_beast/cmd/auth/default.json
algo_beast/cmd/auth/main.json
algo_beast/cmd/commands/__init__.py
algo_beast/cmd/commands/create_project.py
algo_beast/cmd/commands/init.py
algo_beast/cmd/commands/pull.py
algo_beast/cmd/protocols/__init__.py
algo_beast/cmd/protocols/initializer.py
algo_beast/cmd/stubs/.algo-beast/config.json
algo_beast-0.1.7.dist-info/LICENSE
algo_beast-0.1.7.dist-info/METADATA
algo_beast-0.1.7.dist-info/WHEEL
algo_beast-0.1.7.dist-info/entry_points.txt
algo_beast-0.1.7.dist-info/top_level.txt
algo_beast-0.1.7.dist-info/RECORD
